dedupe_FuzzyWuzzy/deduplication.py
dedupe_FuzzyWuzzy-1.0.2.dist-info/LICENSE
dedupe_FuzzyWuzzy-1.0.2.dist-info/METADATA
dedupe_FuzzyWuzzy-1.0.2.dist-info/WHEEL
dedupe_FuzzyWuzzy-1.0.2.dist-info/top_level.txt
dedupe_FuzzyWuzzy-1.0.2.dist-info/RECORD
