Metadata-Version: 2.1
Name: dedupe-FuzzyWuzzy
Version: 1.0.2
Summary: Deduplication using RapidFuzz library.
Home-page: https://github.com/Gandharv30/dedupe-FuzzyWuzzy
Author: Gandharv Pathak
Author-email: pathakgandharv@gmail.com
License: MIT
Platform: UNKNOWN
Requires-Dist: rapidfuzz
Requires-Dist: pandas
